datetime_itertool/__init__.py
datetime_itertool/datetime_iterator.py
datetime_itertool/py.typed
datetime_itertool-0.0.1a0.dist-info/LICENSE
datetime_itertool-0.0.1a0.dist-info/WHEEL
datetime_itertool-0.0.1a0.dist-info/METADATA
datetime_itertool-0.0.1a0.dist-info/RECORD
